<?xml version='1.0' encoding='UTF-8'?>
<faces-config version="3.0" xmlns="https://jakarta.ee/xml/ns/jakartaee"
              xmlns:xsi="http://www.w3.org/2001/XMLSchema-instance"
              xsi:schemaLocation="https://jakarta.ee/xml/ns/jakartaee
                                  https://jakarta.ee/xml/ns/jakartaee/web-facesconfig_3_0.xsd">
    <managed-bean>
        <managed-bean-name>clientBean</managed-bean-name>
        <managed-bean-class>com.crud.Bean.ClientBean</managed-bean-class>
        <managed-bean-scope>view</managed-bean-scope>
    </managed-bean>
    <managed-bean>
        <managed-bean-name>languageBean</managed-bean-name>
        <managed-bean-class>com.crud.Bean.LanguageBean</managed-bean-class>
        <managed-bean-scope>session</managed-bean-scope>
    </managed-bean>
    <validator>
        <validator-id>custom.emailValidator</validator-id>
        <validator-class>com.crud.Validators.EmailValidator</validator-class>
    </validator>
    <validator>
        <validator-id>custom.passwordValidator</validator-id>
        <validator-class>com.crud.Validators.PasswordValidtor</validator-class>
    </validator>
    <validator>
        <validator-id>custom.firstNameValidator</validator-id>
        <validator-class>com.crud.Validators.FirstNameValidtor</validator-class>
    </validator>
    <validator>
        <validator-id>custom.lastNameValidator</validator-id>
        <validator-class>com.crud.Validators.LasteNameValidtor</validator-class>
    </validator>
    <validator>
        <validator-id>custom.phoneNumberValidator</validator-id>
        <validator-class>com.crud.Validators.PhoneValidtor</validator-class>
    </validator>
    <application>
        <locale-config>
            <supported-locale>fr</supported-locale>
            <supported-locale>en</supported-locale>
        </locale-config>
        <resource-bundle>
            <base-name>messages</base-name>
            <var>msg</var>
        </resource-bundle>
    </application>
</faces-config>